micro5125a/__init__.py
micro5125a/micro5125a.py
micro5125a/version.py
micro5125a-0.1.3.data/scripts/micro-5125a
micro5125a-0.1.3.dist-info/METADATA
micro5125a-0.1.3.dist-info/WHEEL
micro5125a-0.1.3.dist-info/top_level.txt
micro5125a-0.1.3.dist-info/RECORD
